gocept.sftpcopy-2.1-py3.9-nspkg.pth
gocept/sftpcopy/__init__.py
gocept/sftpcopy/sftpcopy.py
gocept/sftpcopy/testing.py
gocept/sftpcopy/tests/__init__.py
gocept/sftpcopy/tests/test_sftpcopy.py
gocept.sftpcopy-2.1.dist-info/METADATA
gocept.sftpcopy-2.1.dist-info/WHEEL
gocept.sftpcopy-2.1.dist-info/entry_points.txt
gocept.sftpcopy-2.1.dist-info/namespace_packages.txt
gocept.sftpcopy-2.1.dist-info/top_level.txt
gocept.sftpcopy-2.1.dist-info/RECORD
