Metadata-Version: 2.1
Name: gocept.sftpcopy
Version: 2.1
Summary: Upload/download files via SFTP to a maildir structure
Home-page: https://github.com/gocept/gocept.sftpcopy
Author: Christian Zagrodnick
Author-email: mail@gocept.com
License: ZPL 2.1
Classifier: Development Status :: 5 - Production/Stable
Classifier: Environment :: Console
Classifier: Intended Audience :: Developers
Classifier: License :: OSI Approved
Classifier: Natural Language :: English
Classifier: License :: OSI Approved :: Zope Public License
Classifier: Programming Language :: Python
Classifier: Operating System :: POSIX
Classifier: Operating System :: POSIX :: Linux
Classifier: Operating System :: POSIX :: BSD
Classifier: Operating System :: Unix
Classifier: Programming Language :: Python :: 3
Classifier: Programming Language :: Python :: 3.9
Classifier: Programming Language :: Python :: 3.10
Classifier: Programming Language :: Python :: 3.11
Classifier: Programming Language :: Python :: 3.12
Classifier: Programming Language :: Python :: Implementation :: CPython
Classifier: Topic :: Communications
Classifier: Topic :: Internet
Classifier: Topic :: Internet :: File Transfer Protocol (FTP)
Requires-Dist: setuptools
Requires-Dist: gocept.filestore
Requires-Dist: paramiko
Requires-Dist: configparser ; python_version < "3"
Provides-Extra: test
Requires-Dist: sftpserver ; extra == 'test'
